scidistro_distributions/Binomialdistribution.py
scidistro_distributions/Gaussiandistribution.py
scidistro_distributions/Generaldistribution.py
scidistro_distributions/__init__.py
scidistro_distributions-0.1.dist-info/DESCRIPTION.rst
scidistro_distributions-0.1.dist-info/METADATA
scidistro_distributions-0.1.dist-info/RECORD
scidistro_distributions-0.1.dist-info/WHEEL
scidistro_distributions-0.1.dist-info/metadata.json
scidistro_distributions-0.1.dist-info/top_level.txt
